<?xml version='1.0' encoding='utf-8'?>
<performance>
  <basic>
    <t_uid>094032_071223_1_4510</t_uid>
    <datagram_size>4510</datagram_size>
    <cycle_time>1</cycle_time>
  </basic>
  <test>
    <duration>5.3785</duration>
    <datagrams>663387</datagrams>
    <bandwidth>4450126050.013945</bandwidth>
  </test>
  <timestamps>
    <packet_loss>False</packet_loss>
    <in_order>True</in_order>
    <average_difference>2.1734940764591668e-05</average_difference>
    <standard_deviation>3.5200409055870203e-06</standard_deviation>
    <minimum_difference>1.6561e-05</minimum_difference>
    <maximum_difference>0.000415533</maximum_difference>
    <difference_difference>0.000398972</difference_difference>
    <jitter>9.038590730086968e-07</jitter>
  </timestamps>
</performance>
