<?xml version='1.0' encoding='utf-8'?>
<performance>
  <basic>
    <t_uid>075444_061223_1_41000</t_uid>
    <datagram_size>41000</datagram_size>
    <cycle_time>1</cycle_time>
  </basic>
  <test>
    <duration>5.814457</duration>
    <datagrams>175985</datagrams>
    <bandwidth>9927509997.924139</bandwidth>
  </test>
  <timestamps>
    <packet_loss>False</packet_loss>
    <in_order>False</in_order>
    <average_difference>0.00017569233519902674</average_difference>
    <standard_deviation>2.045224369387535e-05</standard_deviation>
    <minimum_difference>6.9189e-05</minimum_difference>
    <maximum_difference>0.000227047</maximum_difference>
    <difference_difference>0.00015785799999999998</difference_difference>
    <jitter>1.7237666833012214e-05</jitter>
  </timestamps>
</performance>
