<?xml version='1.0' encoding='utf-8'?>
<performance>
  <basic>
    <t_uid>095159_061223_61_80</t_uid>
    <datagram_size>80</datagram_size>
    <cycle_time>61</cycle_time>
  </basic>
  <test>
    <duration>5.479838</duration>
    <datagrams>510855</datagrams>
    <bandwidth>59663661.589995906</bandwidth>
  </test>
  <timestamps>
    <packet_loss>False</packet_loss>
    <in_order>True</in_order>
    <average_difference>2.0261926818764647e-05</average_difference>
    <standard_deviation>2.062989280086064e-06</standard_deviation>
    <minimum_difference>1.5149e-05</minimum_difference>
    <maximum_difference>0.000104358</maximum_difference>
    <difference_difference>8.9209e-05</difference_difference>
    <jitter>1.7609161347539703e-06</jitter>
  </timestamps>
</performance>
